{
 "updated": "2026-06-27",
 "source": "eloratings.net",
 "ratings": {
  "Mexico": 1912,
  "SouthAfrica": 1575,
  "SouthKorea": 1723,
  "Czechia": 1680,
  "Canada": 1748,
  "Switzerland": 1914,
  "Qatar": 1411,
  "Bosnia": 1622,
  "Brazil": 2009,
  "Morocco": 1877,
  "Haiti": 1517,
  "Scotland": 1745,
  "USA": 1781,
  "Australia": 1800,
  "Paraguay": 1815,
  "Turkiye": 1852,
  "Germany": 1916,
  "Curacao": 1438,
  "IvoryCoast": 1743,
  "Ecuador": 1902,
  "Netherlands": 1980,
  "Japan": 1910,
  "Sweden": 1742,
  "Tunisia": 1562,
  "Belgium": 1869,
  "Egypt": 1740,
  "Iran": 1766,
  "NewZealand": 1549,
  "Spain": 2144,
  "CapeVerde": 1622,
  "SaudiArabia": 1596,
  "Uruguay": 1841,
  "France": 2123,
  "Senegal": 1842,
  "Iraq": 1561,
  "Norway": 1918,
  "Argentina": 2144,
  "Algeria": 1780,
  "Austria": 1841,
  "Jordan": 1632,
  "Portugal": 1988,
  "DRCongo": 1666,
  "Uzbekistan": 1677,
  "Colombia": 2006,
  "England": 2028,
  "Croatia": 1896,
  "Ghana": 1584,
  "Panama": 1668
 }
}
